Workbook

Sheet Data Cleaning Start
B2: Date | C2: Client | D2: Contact | E2: Department | F2: Payment | G2: Revenue | H2: Profit | I2: Profit Margin
B3: 45076 | C3: AMAZON.COM, INC. (XNAS:AMZN) | D3: Bill SmITH | E3: Cloud Tech_Texas | F3: Transfer | G3: 4500 | H3: 598 | I3: =H3/G3 -> 0.13288889
B4: 45076 | C4: TESLA, INC. (XNAS:TSLA) | D4: KEN Singh | E4: Strategy_New York | F4: PayPal | G4: 3800 | H4: 1045 | I4: =H4/G4 -> 0.275
B5: 45076 | C5: NETFLIX, INC. (XNAS:NFLX) | D5: Harley Fritz | E5: Strategy_New York | G5: 3712.5 | H5: 1009 | I5: =H5/G5 -> 0.27178451
B6: 45076 | C6: THE PROCTER & GAMBLE COMPANY (XNYS:PG) | D6: Nyla Novak | E6: Operations_Florida | H6: 779 | I6: =H6/G6 -> #DIV/0!
B7: 45076 | C7: THE GOLDMAN SACHS GROUP, INC. (XNYS:GS) | D7: David Rasmussen | E7: Operations_Florida | F7: Check | G7: 5000 | H7: 684 | I7: =H7/G7 -> 0.1368
B8: 45077 | C8: JPMORGAN CHASE & CO. (XNYS:JPM) | D8: IVAN HINEY | E8: Cloud Tech_Texas | F8: Transfer | G8: 6100 | H8: 544 | I8: =H8/G8 -> 0.089180328
B9: 45077 | C9: MORGAN STANLEY (XNYS:MS) | D9: JONha Ma | E9: Cloud Tech_Texas | F9: Transfer | G9: 4625 | H9: 670 | I9: =H9/G9 -> 0.14486486
B10: 45077 | C10: CITIGROUP INC. (XNYS:C) | D10: Jordan Boone | E10: Cloud Tech_Texas | F10: Transfer | G10: 3800 | H10: 2045 | I10: =H10/G10 -> 0.53815789
B11: 45077 | C11: BANK OF AMERICA CORPORATION (XNYS:BAC) | D11: Kylee Townsend | E11: Cloud Tech_Texas | F11: Card | G11: 3600 | H11: 1564 | I11: =H11/G11 -> 0.43444444
B12: 45077 | C12: WALMART INC. (XNYS:WMT) | D12: Nora Rollins | E12: Cloud Tech_Texas | F12: Check | G12: 5100 | H12: 1220 | I12: =H12/G12 -> 0.23921569
B13: 45077 | C13: TARGET CORPORATION (XNYS:TGT) | D13: BRENDAN Wallace | E13: Cloud Tech_Texas | F13: Check | G13: 4750 | H13: 1435 | I13: =H13/G13 -> 0.30210526
B14: 45077 | C14: COSTCO WHOLESALE CORPORATION (XNAS:COST) | D14: Conor Wise | E14: Operations_Florida | F14: Transfer | G14: 6000 | H14: 998 | I14: =H14/G14 -> 0.16633333
B15: 45077 | C15: MCDONALD'S CORPORATION (XNYS:MCD) | D15: Steven MIChael | E15: Big Data_California | F15: Check | G15: 4500 | H15: 780 | I15: =H15/G15 -> 0.17333333
B16: 45078 | C16: EXXON MOBIL CORPORATION (XNYS:XOM) | D16: Lucia Mckay | E16: Big Data_California | F16: Card | H16: 1044 | I16: =H16/G16 -> #DIV/0!
B17: 45078 | C17: VERIZON COMMUNICATIONS INC. (XNYS:VZ) | D17: JoSE Roach | E17: Big Data_California | F17: Transfer | G17: 3712.5 | H17: 1222 | I17: =H17/G17 -> 0.32915825
B18: 45078 | C18: THE HOME DEPOT, INC. (XNYS:HD) | D18: Franklin WRIGT | E18: Big Data_California | F18: Transfer | G18: 4950 | H18: 1065 | I18: =H18/G18 -> 0.21515152
B19: 45078 | C19: CISCO SYSTEMS, INC. (XNAS:CSCO) | D19: Alia Thornton | E19: Operations_Florida | F19: Transfer | G19: 4750 | H19: 810 | I19: =H19/G19 -> 0.17052632
B20: 45078 | C20: CHEVRON CORPORATION (XNYS:CVX) | D20: Denzel Flores | E20: Operations_Florida | F20: Transfer | G20: 7320 | H20: 933 | I20: =H20/G20 -> 0.12745902
B21: 45077 | C21: COSTCO WHOLESALE CORPORATION (XNAS:COST) | D21: Conor Wise | E21: Operations_Florida | F21: Transfer | G21: 6000 | H21: 998 | I21: =H21/G21 -> 0.16633333
B22: 45077 | C22: MCDONALD'S CORPORATION (XNYS:MCD) | D22: Steven MIChael | E22: Big Data_California | F22: Check | G22: 4500 | H22: 780 | I22: =H22/G22 -> 0.17333333
B23: 45078 | C23: AT&T INC. (XNYS:T) | D23: Bruno CordOVA | E23: Big Data_California | F23: Transfer | G23: 5087.5 | H23: 655 | I23: =H23/G23 -> 0.12874693
B24: 45078 | C24: INTEL CORPORATION (XNAS:INTC) | D24: jaylynn napp | E24: Big Data_California | F24: Transfer | G24: 4500 | H24: 722 | I24: =H24/G24 -> 0.16044444
B25: 45078 | C25: GENERAL MOTORS COMPANY (XNYS:GM) | D25: Bruce RICH | E25: Big Data_California | F25: Card | G25: 4250 | H25: 901 | I25: =H25/G25 -> 0.212
B26: 45079 | C26: MICROSOFT CORPORATION (XNAS:MSFT) | D26: Arturo Moore | E26: Big Data_California | F26: PayPal | G26: 5250 | H26: 1349 | I26: =H26/G26 -> 0.25695238
B27: 45079 | C27: COMCAST CORPORATION (XNAS:CMCSA) | D27: Bryce Carpenter | E27: Strategy_New York | F27: PayPal | G27: 6500 | H27: 1288 | I27: =H27/G27 -> 0.19815385
B28: 45079 | C28: DELL TECHNOLOGIES INC. (XNYS:DELL) | D28: Jaidyn ANDERSEN | E28: Strategy_New York | F28: PayPal | G28: 7500 | H28: 1664 | I28: =H28/G28 -> 0.22186667
... B33: 45076 | C33: THE GOLDMAN SACHS GROUP, INC. (XNYS:GS) | D33: David Rasmussen | E33: Operations_Florida | F33: Check | G33: 5000 | H33: 684 | I33: =H33/G33 -> 0.1368

Sheet Data Cleaning Start (2)
A2: trans_id | B2: Date | C2: client_id | D2: Contact | E2: department_id | F2: state_id | G2: payment_id | H2: Revenue | I2: Profit | J2: Profit Margin
A3: t-101 | B3: 45076 | C3: AMAZON.COM, INC. | D3: Bill Smith | E3: Cloud Tech | F3: Texas | G3: Transfer | H3: 4500 | I3: 598 | J3: =IFERROR(I3/H3,0) -> 0.13288889
A4: t-102 | B4: 45076 | C4: TESLA, INC. | D4: Ken Singh | E4: Strategy | F4: New York | G4: PayPal | H4: 3800 | I4: 1045 | J4: =IFERROR(I4/H4,0) -> 0.275
A5: t-103 | B5: 45076 | C5: NETFLIX, INC. | D5: Harley Fritz | E5: Strategy | F5: New York | G5: Others | H5: 3712.5 | I5: 1009 | J5: =J7 -> 0.1368
A6: t-104 | B6: 45076 | C6: THE PROCTER & GAMBLE COMPANY | D6: Nyla Novak | E6: Operations | F6: Florida | G6: Others | H6: 4994 | I6: 779 | J6: =IFERROR(I6/H6,0) -> 0.15598718
A7: t-105 | B7: 45076 | C7: THE GOLDMAN SACHS GROUP, INC. | D7: David Rasmussen | E7: Operations | F7: Florida | G7: Check | H7: 5000 | I7: 684 | J7: =IFERROR(I7/H7,0) -> 0.1368
A8: t-106 | B8: 45077 | C8: JPMORGAN CHASE & CO. | D8: Ivan Hiney | E8: Cloud Tech | F8: Texas | G8: Transfer | H8: 6100 | I8: 544 | J8: =IFERROR(I8/H8,0) -> 0.089180328
A9: t-107 | B9: 45077 | C9: MORGAN STANLEY | D9: Jonha Ma | E9: Cloud Tech | F9: Texas | G9: Transfer | H9: 4625 | I9: 670 | J9: =IFERROR(I9/H9,0) -> 0.14486486
A10: t-108 | B10: 45077 | C10: CITIGROUP INC. | D10: Jordan Boone | E10: Cloud Tech | F10: Texas | G10: Transfer | H10: 3800 | I10: 2045 | J10: =IFERROR(I10/H10,0) -> 0.53815789
A11: t-109 | B11: 45077 | C11: BANK OF AMERICA CORPORATION | D11: Kylee Townsend | E11: Cloud Tech | F11: Texas | G11: Card | H11: 3600 | I11: 1564 | J11: =IFERROR(I11/H11,0) -> 0.43444444
A12: t-110 | B12: 45077 | C12: WALMART INC. | D12: Nora Rollins | E12: Cloud Tech | F12: Texas | G12: Check | H12: 5100 | I12: 1220 | J12: =IFERROR(I12/H12,0) -> 0.23921569
A13: t-111 | B13: 45077 | C13: TARGET CORPORATION | D13: Brendan Wallace | E13: Cloud Tech | F13: Texas | G13: Check | H13: 4750 | I13: 1435 | J13: =IFERROR(I13/H13,0) -> 0.30210526
A14: t-112 | B14: 45077 | C14: COSTCO WHOLESALE CORPORATION | D14: Conor Wise | E14: Operations | F14: Florida | G14: Transfer | H14: 6000 | I14: 998 | J14: =IFERROR(I14/H14,0) -> 0.16633333
A15: t-113 | B15: 45077 | C15: MCDONALD'S CORPORATION | D15: Steven Michael | E15: Big Data | F15: California | G15: Check | H15: 4500 | I15: 780 | J15: =IFERROR(I15/H15,0) -> 0.17333333
A16: t-114 | B16: 45078 | C16: EXXON MOBIL CORPORATION | D16: Lucia Mckay | E16: Big Data | F16: California | G16: Card | H16: 4994 | I16: 1044 | J16: =IFERROR(I16/H16,0) -> 0.20905086
A17: t-115 | B17: 45078 | C17: VERIZON COMMUNICATIONS INC. | D17: Jose Roach | E17: Big Data | F17: California | G17: Transfer | H17: 3712.5 | I17: 1222 | J17: =IFERROR(I17/H17,0) -> 0.32915825
... A30: t-128 | B30: 45079 | C30: LOCKHEED MARTIN CORPORATION | D30: Mik Naam | E30: Strategy | F30: New York | G30: Card | H30: 5400 | I30: 540 | J30: =IFERROR(I30/H30,0) -> 0.1
H34: =AVERAGE(H3:H33) -> 4975.7321

Sheet Client
A2: Client | B2: client_id | C2: Contact
A3: AMAZON.COM, INC. | B3: c-101 | C3: Bill Smith
A4: AT&T INC. | B4: c-102 | C4: Bruno Cordova
A5: BANK OF AMERICA CORPORATION | B5: c-103 | C5: Kylee Townsend
A6: CHEVRON CORPORATION | B6: c-104 | C6: Denzel Flores
A7: CISCO SYSTEMS, INC. | B7: c-105 | C7: Alia Thornton
A8: CITIGROUP INC. | B8: c-106 | C8: Jordan Boone
A9: COMCAST CORPORATION | B9: c-107 | C9: Bryce Carpenter
A10: COSTCO WHOLESALE CORPORATION | B10: c-108 | C10: Conor Wise
A11: DELL TECHNOLOGIES INC. | B11: c-109 | C11: Jaidyn Andersen
A12: EXXON MOBIL CORPORATION | B12: c-110 | C12: Lucia Mckay
A13: FEDEX CORPORATION | B13: c-111 | C13: Harry Lee
... A30: WALMART INC. | B30: c-128 | C30: Nora Rollins

Sheet State
A2: States | B2: state_id
A3: California | B3: s-101
A4: Florida | B4: s-102
A5: New York | B5: s-104
A6: Texas | B6: s-113

Sheet Payment
A2: payment_id | B2: Payment
A3: p-101 | B3: Transfer
A4: p-102 | B4: Card
A5: p-103 | B5: Check
A6: p-105 | B6: Others
A7: p-109 | B7: PayPal

Sheet Department
A2: Department | B2: department_id
A3: Big Data | B3: d-101
A4: Cloud Tech | B4: d-102
A5: Operations | B5: d-104
A6: Strategy | B6: d-113

Sheet VLookUp
A2: trans_id | B2: Date | C2: client_id | D2: Client | E2: Contact | F2: department_id | G2: Department | H2: state_id | I2: State | J2: payment_id | K2: Revenue | L2: Profit | M2: Profit Margin
A3: t-101 | B3: 45076 | C3: =VLOOKUP(D3,Client!A$3:C$30,2,FALSE) -> c-101 | D3: AMAZON.COM, INC. | E3: Bill Smith | F3: =VLOOKUP(G3,Department!A$3:B$6,2,FALSE) -> d-102 | G3: Cloud Tech | H3: =VLOOKUP(I3,State!A$3:B$6,2,FALSE) -> s-113 | I3: Texas | J3: Transfer | K3: 4500 | L3: 598 | M3: =IFERROR(L3/K3,0) -> 0.13288889
A4: t-102 | B4: 45076 | C4: =VLOOKUP(D4,Client!A$3:C$30,2,FALSE) -> c-123 | D4: TESLA, INC. | E4: Ken Singh | F4: =VLOOKUP(G4,Department!A$3:B$6,2,FALSE) -> d-113 | G4: Strategy | H4: =VLOOKUP(I4,State!A$3:B$6,2,FALSE) -> s-104 | I4: New York | J4: PayPal | K4: 3800 | L4: 1045 | M4: =IFERROR(L4/K4,0) -> 0.275
A5: t-103 | B5: 45076 | C5: =VLOOKUP(D5,Client!A$3:C$30,2,FALSE) -> c-121 | D5: NETFLIX, INC. | E5: Harley Fritz | F5: =VLOOKUP(G5,Department!A$3:B$6,2,FALSE) -> d-113 | G5: Strategy | H5: =VLOOKUP(I5,State!A$3:B$6,2,FALSE) -> s-104 | I5: New York | J5: Others | K5: 3712.5 | L5: 1009 | M5: =M7 -> 0.1368
A6: t-104 | B6: 45076 | C6: =VLOOKUP(D6,Client!A$3:C$30,2,FALSE) -> c-126 | D6: THE PROCTER & GAMBLE COMPANY | E6: Nyla Novak | F6: =VLOOKUP(G6,Department!A$3:B$6,2,FALSE) -> d-104 | G6: Operations | H6: =VLOOKUP(I6,State!A$3:B$6,2,FALSE) -> s-102 | I6: Florida | J6: Others | K6: 4994 | L6: 779 | M6: =IFERROR(L6/K6,0) -> 0.15598718
A7: t-105 | B7: 45076 | C7: =VLOOKUP(D7,Client!A$3:C$30,2,FALSE) -> c-124 | D7: THE GOLDMAN SACHS GROUP, INC. | E7: David Rasmussen | F7: =VLOOKUP(G7,Department!A$3:B$6,2,FALSE) -> d-104 | G7: Operations | H7: =VLOOKUP(I7,State!A$3:B$6,2,FALSE) -> s-102 | I7: Florida | J7: Check | K7: 5000 | L7: 684 | M7: =IFERROR(L7/K7,0) -> 0.1368
A8: t-106 | B8: 45077 | C8: =VLOOKUP(D8,Client!A$3:C$30,2,FALSE) -> c-116 | D8: JPMORGAN CHASE & CO. | E8: Ivan Hiney | F8: =VLOOKUP(G8,Department!A$3:B$6,2,FALSE) -> d-102 | G8: Cloud Tech | H8: =VLOOKUP(I8,State!A$3:B$6,2,FALSE) -> s-113 | I8: Texas | J8: Transfer | K8: 6100 | L8: 544 | M8: =IFERROR(L8/K8,0) -> 0.089180328
A9: t-107 | B9: 45077 | C9: =VLOOKUP(D9,Client!A$3:C$30,2,FALSE) -> c-120 | D9: MORGAN STANLEY | E9: Jonha Ma | F9: =VLOOKUP(G9,Department!A$3:B$6,2,FALSE) -> d-102 | G9: Cloud Tech | H9: =VLOOKUP(I9,State!A$3:B$6,2,FALSE) -> s-113 | I9: Texas | J9: Transfer | K9: 4625 | L9: 670 | M9: =IFERROR(L9/K9,0) -> 0.14486486
A10: t-108 | B10: 45077 | C10: =VLOOKUP(D10,Client!A$3:C$30,2,FALSE) -> c-106 | D10: CITIGROUP INC. | E10: Jordan Boone | F10: =VLOOKUP(G10,Department!A$3:B$6,2,FALSE) -> d-102 | G10: Cloud Tech | H10: =VLOOKUP(I10,State!A$3:B$6,2,FALSE) -> s-113 | I10: Texas | J10: Transfer | K10: 3800 | L10: 2045 | M10: =IFERROR(L10/K10,0) -> 0.53815789
A11: t-109 | B11: 45077 | C11: =VLOOKUP(D11,Client!A$3:C$30,2,FALSE) -> c-103 | D11: BANK OF AMERICA CORPORATION | E11: Kylee Townsend | F11: =VLOOKUP(G11,Department!A$3:B$6,2,FALSE) -> d-102 | G11: Cloud Tech | H11: =VLOOKUP(I11,State!A$3:B$6,2,FALSE) -> s-113 | I11: Texas | J11: Card | K11: 3600 | L11: 1564 | M11: =IFERROR(L11/K11,0) -> 0.43444444
A12: t-110 | B12: 45077 | C12: =VLOOKUP(D12,Client!A$3:C$30,2,FALSE) -> c-128 | D12: WALMART INC. | E12: Nora Rollins | F12: =VLOOKUP(G12,Department!A$3:B$6,2,FALSE) -> d-102 | G12: Cloud Tech | H12: =VLOOKUP(I12,State!A$3:B$6,2,FALSE) -> s-113 | I12: Texas | J12: Check | K12: 5100 | L12: 1220 | M12: =IFERROR(L12/K12,0) -> 0.23921569
A13: t-111 | B13: 45077 | C13: =VLOOKUP(D13,Client!A$3:C$30,2,FALSE) -> c-122 | D13: TARGET CORPORATION | E13: Brendan Wallace | F13: =VLOOKUP(G13,Department!A$3:B$6,2,FALSE) -> d-102 | G13: Cloud Tech | H13: =VLOOKUP(I13,State!A$3:B$6,2,FALSE) -> s-113 | I13: Texas | J13: Check | K13: 4750 | L13: 1435 | M13: =IFERROR(L13/K13,0) -> 0.30210526
A14: t-112 | B14: 45077 | C14: =VLOOKUP(D14,Client!A$3:C$30,2,FALSE) -> c-108 | D14: COSTCO WHOLESALE CORPORATION | E14: Conor Wise | F14: =VLOOKUP(G14,Department!A$3:B$6,2,FALSE) -> d-104 | G14: Operations | H14: =VLOOKUP(I14,State!A$3:B$6,2,FALSE) -> s-102 | I14: Florida | J14: Transfer | K14: 6000 | L14: 998 | M14: =IFERROR(L14/K14,0) -> 0.16633333
A15: t-113 | B15: 45077 | C15: =VLOOKUP(D15,Client!A$3:C$30,2,FALSE) -> c-118 | D15: MCDONALD'S CORPORATION | E15: Steven Michael | F15: =VLOOKUP(G15,Department!A$3:B$6,2,FALSE) -> d-101 | G15: Big Data | H15: =VLOOKUP(I15,State!A$3:B$6,2,FALSE) -> s-101 | I15: California | J15: Check | K15: 4500 | L15: 780 | M15: =IFERROR(L15/K15,0) -> 0.17333333
A16: t-114 | B16: 45078 | C16: =VLOOKUP(D16,Client!A$3:C$30,2,FALSE) -> c-110 | D16: EXXON MOBIL CORPORATION | E16: Lucia Mckay | F16: =VLOOKUP(G16,Department!A$3:B$6,2,FALSE) -> d-101 | G16: Big Data | H16: =VLOOKUP(I16,State!A$3:B$6,2,FALSE) -> s-101 | I16: California | J16: Card | K16: 4994 | L16: 1044 | M16: =IFERROR(L16/K16,0) -> 0.20905086
A17: t-115 | B17: 45078 | C17: =VLOOKUP(D17,Client!A$3:C$30,2,FALSE) -> c-127 | D17: VERIZON COMMUNICATIONS INC. | E17: Jose Roach | F17: =VLOOKUP(G17,Department!A$3:B$6,2,FALSE) -> d-101 | G17: Big Data | H17: =VLOOKUP(I17,State!A$3:B$6,2,FALSE) -> s-101 | I17: California | J17: Transfer | K17: 3712.5 | L17: 1222 | M17: =IFERROR(L17/K17,0) -> 0.32915825
... A30: t-128 | B30: 45079 | C30: =VLOOKUP(D30,Client!A$3:C$30,2,FALSE) -> c-117 | D30: LOCKHEED MARTIN CORPORATION | E30: Mik Naam | F30: =VLOOKUP(G30,Department!A$3:B$6,2,FALSE) -> d-113 | G30: Strategy | H30: =VLOOKUP(I30,State!A$3:B$6,2,FALSE) -> s-104 | I30: New York | J30: Card | K30: 5400 | L30: 540 | M30: =IFERROR(L30/K30,0) -> 0.1
K34: =AVERAGE(K3:K33) -> 4975.7321
